edgegraph/__init__.py
edgegraph/version.py
edgegraph/builder/__init__.py
edgegraph/builder/adjlist.py
edgegraph/builder/adjmatrix.py
edgegraph/builder/explicit.py
edgegraph/builder/randgraph.py
edgegraph/output/__init__.py
edgegraph/output/nrpickler.py
edgegraph/output/plaintext.py
edgegraph/output/plantuml.py
edgegraph/output/pyvis.py
edgegraph/pathfinding/__init__.py
edgegraph/pathfinding/shortestpath.py
edgegraph/structure/__init__.py
edgegraph/structure/base.py
edgegraph/structure/directededge.py
edgegraph/structure/link.py
edgegraph/structure/singleton.py
edgegraph/structure/twoendedlink.py
edgegraph/structure/undirectededge.py
edgegraph/structure/universe.py
edgegraph/structure/vertex.py
edgegraph/traversal/__init__.py
edgegraph/traversal/breadthfirst.py
edgegraph/traversal/depthfirst.py
edgegraph/traversal/helpers.py
edgegraph-0.11.0.dist-info/licenses/LICENSE.txt
edgegraph-0.11.0.dist-info/METADATA
edgegraph-0.11.0.dist-info/WHEEL
edgegraph-0.11.0.dist-info/top_level.txt
edgegraph-0.11.0.dist-info/RECORD
