Metadata-Version: 2.4
Name: edgegraph
Version: 0.11.0
Summary: Object oriented edge-vertex graph library.
License:                    GNU LESSER GENERAL PUBLIC LICENSE
Project-URL: Homepage, https://edgegraph.readthedocs.io/en/latest/
Project-URL: Repository, https://github.com/mishaturnbull/edgegraph
Classifier: Development Status :: 4 - Beta
Classifier: Intended Audience :: Developers
Classifier: Operating System :: OS Independent
Classifier: Programming Language :: Python :: 3 :: Only
Classifier: Topic :: Software Development :: Libraries :: Python Modules
Requires-Python: >=3.7
License-File: LICENSE.txt
Requires-Dist: dill
Provides-Extra: foreign
Requires-Dist: pyvis; extra == "foreign"
Provides-Extra: full
Requires-Dist: edgegraph[foreign]; extra == "full"
Provides-Extra: development
Requires-Dist: sphinxcontrib-plantuml; extra == "development"
Requires-Dist: sphinx-copybutton; extra == "development"
Requires-Dist: sphinx-book-theme; extra == "development"
Requires-Dist: myst-parser; extra == "development"
Requires-Dist: tomlkit; extra == "development"
Requires-Dist: pytest; extra == "development"
Requires-Dist: coverage; extra == "development"
Requires-Dist: pytest-cov; extra == "development"
Requires-Dist: pytest-profiling; extra == "development"
Requires-Dist: pytest-randomly; extra == "development"
Requires-Dist: pytest-timeout; extra == "development"
Requires-Dist: pylint; extra == "development"
Requires-Dist: black; extra == "development"
Requires-Dist: mypy; extra == "development"
Requires-Dist: edgegraph[full]; extra == "development"
Provides-Extra: administer
Requires-Dist: build; extra == "administer"
Requires-Dist: twine; extra == "administer"
Requires-Dist: edgegraph[development]; extra == "administer"
Dynamic: license-file
